elektronn3/__init__.py
elektronn3/_version.py
elektronn3/logger.py
elektronn3/data/__init__.py
elektronn3/data/cnndata.py
elektronn3/data/coord_transforms.py
elektronn3/data/knossos.py
elektronn3/data/knossos_labels.py
elektronn3/data/sources.py
elektronn3/data/utils.py
elektronn3/data/transforms/__init__.py
elektronn3/data/transforms/functional.py
elektronn3/data/transforms/random.py
elektronn3/data/transforms/random_blurring.py
elektronn3/data/transforms/region_generator.py
elektronn3/data/transforms/transforms.py
elektronn3/inference/__init__.py
elektronn3/inference/inference.py
elektronn3/models/__init__.py
elektronn3/models/_model_utils.py
elektronn3/models/base.py
elektronn3/models/fcn.py
elektronn3/models/fcn_2d.py
elektronn3/models/msdnet.py
elektronn3/models/resunet.py
elektronn3/models/simple.py
elektronn3/models/tiramisu_2d.py
elektronn3/models/unet.py
elektronn3/models/unet3d_lite.py
elektronn3/models/vnet.py
elektronn3/modules/__init__.py
elektronn3/modules/axial_attention.py
elektronn3/modules/evonorm.py
elektronn3/modules/l1batchnorm.py
elektronn3/modules/layers.py
elektronn3/modules/loss.py
elektronn3/modules/lovasz_losses.py
elektronn3/modules/wsconv.py
elektronn3/training/__init__.py
elektronn3/training/_trainer_multi.py
elektronn3/training/handlers.py
elektronn3/training/metrics.py
elektronn3/training/noise2void.py
elektronn3/training/padam.py
elektronn3/training/plotting.py
elektronn3/training/recalibration.py
elektronn3/training/swa.py
elektronn3/training/train_utils.py
elektronn3/training/trainer.py
elektronn3/training/trainer_gnn.py
elektronn3/training/trainer_gnn_batch.py
elektronn3/training/trainer_gnn_minibatch.py
elektronn3/training/triplettrainer.py
elektronn3-0.1.1.dist-info/LICENSE
elektronn3-0.1.1.dist-info/METADATA
elektronn3-0.1.1.dist-info/WHEEL
elektronn3-0.1.1.dist-info/top_level.txt
elektronn3-0.1.1.dist-info/RECORD
