Metadata-Version: 2.1
Name: elektronn3
Version: 0.1.1
Summary: Utilities for 3D CNNs in PyTorch
Home-page: https://github.com/ELEKTRONN/elektronn3
Author: ELEKTRONN team
License: MIT
Classifier: Development Status :: 3 - Alpha
Classifier: License :: OSI Approved :: MIT License
Classifier: Programming Language :: Python :: 3
Classifier: Programming Language :: Python :: 3.6
Classifier: Programming Language :: Python :: 3.7
License-File: LICENSE
Requires-Dist: torch
Requires-Dist: numpy
Requires-Dist: scipy
Requires-Dist: h5py
Requires-Dist: matplotlib
Requires-Dist: numba
Requires-Dist: ipython
Requires-Dist: imageio
Requires-Dist: colorlog
Requires-Dist: tqdm
Requires-Dist: scikit-learn
Requires-Dist: scikit-image
Requires-Dist: tensorboardX
Requires-Dist: torchvision
